[
  {
    "TaxCode": "2249954342",
    "Name": "Perkle",
    "ShortName": "Pe.le",
    "Country": "Vatican City State (Holy See)",
    "CompanyType": "SMB",
    "Address": "424 Harman Street, Bancroft, Puerto Rico, 7641",
    "StartYear": 2019,
    "TelephoneNumber": "(84+) 898-4482",
    "Email": "lourdesmcleod@perkle.com",
    "Website": "http://placehold.it/32x32",
    "BusinessType": "Sole proprietorship",
    "MainCarrer": "a",
    "RegisteredCapital": 248004.06,
    "InvestedCapital": 286058.47,
    "CharterCapital": 340831.98,
    "OwnerId": 8
  },
  {
    "TaxCode": "4208523622",
    "Name": "Corporana",
    "ShortName": "Co.or",
    "Country": "Panama",
    "CompanyType": "SMB",
    "Address": "772 Oxford Walk, Goochland, Northern Mariana Islands, 2388",
    "StartYear": 2015,
    "TelephoneNumber": "(84+) 877-4033",
    "Email": "lourdesmcleod@corporana.com",
    "Website": "http://placehold.it/32x32",
    "BusinessType": "Sole proprietorship",
    "MainCarrer": "b",
    "RegisteredCapital": 188483.43,
    "InvestedCapital": 323072.59,
    "CharterCapital": 223703.89,
    "OwnerId": 11
  },
  {
    "TaxCode": "8334575768",
    "Name": "Quilm",
    "ShortName": "Qu.m",
    "Country": "Sao Tome and Principe",
    "CompanyType": "SMB",
    "Address": "761 Portal Street, Westerville, Maryland, 6565",
    "StartYear": 2017,
    "TelephoneNumber": "(84+) 962-5703",
    "Email": "lourdesmcleod@quilm.com",
    "Website": "http://placehold.it/32x32",
    "BusinessType": "Partnership",
    "MainCarrer": "b",
    "RegisteredCapital": 298805.52,
    "InvestedCapital": 275569.7,
    "CharterCapital": 190088.62,
    "OwnerId": 11
  },
  {
    "TaxCode": "6857213472",
    "Name": "Inear",
    "ShortName": "In.r",
    "Country": "Bulgaria",
    "CompanyType": "Large enterprise",
    "Address": "355 Throop Avenue, Marbury, Utah, 2472",
    "StartYear": 1999,
    "TelephoneNumber": "(84+) 808-5063",
    "Email": "lourdesmcleod@inear.com",
    "Website": "http://placehold.it/32x32",
    "BusinessType": " LLC",
    "MainCarrer": "b",
    "RegisteredCapital": 272321.24,
    "InvestedCapital": 124701.13,
    "CharterCapital": 327523.47,
    "OwnerId": 4
  },
  {
    "TaxCode": "3925333375",
    "Name": "Puria",
    "ShortName": "Pu.a",
    "Country": "Faroe Islands",
    "CompanyType": "SMB",
    "Address": "795 Love Lane, Goodville, Colorado, 9131",
    "StartYear": 2012,
    "TelephoneNumber": "(84+) 882-5192",
    "Email": "lourdesmcleod@puria.com",
    "Website": "http://placehold.it/32x32",
    "BusinessType": "Sole proprietorship",
    "MainCarrer": "a",
    "RegisteredCapital": 196920.78,
    "InvestedCapital": 213281.49,
    "CharterCapital": 311140.72,
    "OwnerId": 8
  },
  {
    "TaxCode": "2641515246",
    "Name": "Comverges",
    "ShortName": "Co.er",
    "Country": "Morocco",
    "CompanyType": "Large enterprise",
    "Address": "246 Vermont Street, Bowden, Minnesota, 5331",
    "StartYear": 2012,
    "TelephoneNumber": "(84+) 895-4583",
    "Email": "lourdesmcleod@comverges.com",
    "Website": "http://placehold.it/32x32",
    "BusinessType": " LLC",
    "MainCarrer": "b",
    "RegisteredCapital": 190348.28,
    "InvestedCapital": 152856.68,
    "CharterCapital": 166949.73,
    "OwnerId": 7
  },
  {
    "TaxCode": "2954395574",
    "Name": "Momentia",
    "ShortName": "Mo.nt",
    "Country": "Kazakhstan",
    "CompanyType": "SMB",
    "Address": "547 Newton Street, Martinsville, Florida, 7905",
    "StartYear": 2003,
    "TelephoneNumber": "(84+) 864-4503",
    "Email": "lourdesmcleod@momentia.com",
    "Website": "http://placehold.it/32x32",
    "BusinessType": "Partnership",
    "MainCarrer": "c",
    "RegisteredCapital": 209911.92,
    "InvestedCapital": 209675.88,
    "CharterCapital": 268808.81,
    "OwnerId": 11
  },
  {
    "TaxCode": "9389163237",
    "Name": "Nutralab",
    "ShortName": "Nu.al",
    "Country": "British Indian Ocean Territory",
    "CompanyType": "SME",
    "Address": "746 Bay Street, Nutrioso, Federated States Of Micronesia, 2022",
    "StartYear": 2019,
    "TelephoneNumber": "(84+) 978-5383",
    "Email": "lourdesmcleod@nutralab.com",
    "Website": "http://placehold.it/32x32",
    "BusinessType": "Partnership",
    "MainCarrer": "c",
    "RegisteredCapital": 311202.55,
    "InvestedCapital": 155527.68,
    "CharterCapital": 291388.27,
    "OwnerId": 13
  },
  {
    "TaxCode": "7922477363",
    "Name": "Biolive",
    "ShortName": "Bi.iv",
    "Country": "Namibia",
    "CompanyType": "Large enterprise",
    "Address": "422 Keap Street, Clarksburg, Arkansas, 6830",
    "StartYear": 2014,
    "TelephoneNumber": "(84+) 829-4872",
    "Email": "lourdesmcleod@biolive.com",
    "Website": "http://placehold.it/32x32",
    "BusinessType": "Partnership",
    "MainCarrer": "b",
    "RegisteredCapital": 368561.08,
    "InvestedCapital": 383237.5,
    "CharterCapital": 209167.88,
    "OwnerId": 20
  },
  {
    "TaxCode": "5205901829",
    "Name": "Orbiflex",
    "ShortName": "Or.fl",
    "Country": "Martinique",
    "CompanyType": "SME",
    "Address": "733 Hendrix Street, Outlook, Georgia, 3123",
    "StartYear": 2012,
    "TelephoneNumber": "(84+) 984-4593",
    "Email": "lourdesmcleod@orbiflex.com",
    "Website": "http://placehold.it/32x32",
    "BusinessType": "Sole proprietorship",
    "MainCarrer": "c",
    "RegisteredCapital": 114307.07,
    "InvestedCapital": 112782.61,
    "CharterCapital": 358122.49,
    "OwnerId": 8
  },
  {
    "TaxCode": "0958932046",
    "Name": "Orboid",
    "ShortName": "Or.id",
    "Country": "Togo",
    "CompanyType": "Large enterprise",
    "Address": "632 Varanda Place, Klagetoh, Tennessee, 8644",
    "StartYear": 2012,
    "TelephoneNumber": "(84+) 998-5182",
    "Email": "lourdesmcleod@orboid.com",
    "Website": "http://placehold.it/32x32",
    "BusinessType": "Partnership",
    "MainCarrer": "a",
    "RegisteredCapital": 231166.67,
    "InvestedCapital": 253943.16,
    "CharterCapital": 176562.64,
    "OwnerId": 1
  },
  {
    "TaxCode": "8360496616",
    "Name": "Xeronk",
    "ShortName": "Xe.nk",
    "Country": "Nigeria",
    "CompanyType": "SME",
    "Address": "992 Bergen Street, Worcester, South Dakota, 4029",
    "StartYear": 2006,
    "TelephoneNumber": "(84+) 912-5823",
    "Email": "lourdesmcleod@xeronk.com",
    "Website": "http://placehold.it/32x32",
    "BusinessType": "corporation",
    "MainCarrer": "a",
    "RegisteredCapital": 245273.76,
    "InvestedCapital": 298245.38,
    "CharterCapital": 315278.9,
    "OwnerId": 14
  },
  {
    "TaxCode": "8679362326",
    "Name": "Qualitex",
    "ShortName": "Qu.it",
    "Country": "Burkina Faso",
    "CompanyType": "Large enterprise",
    "Address": "790 Hudson Avenue, Fivepointville, Iowa, 3055",
    "StartYear": 2004,
    "TelephoneNumber": "(84+) 948-4902",
    "Email": "lourdesmcleod@qualitex.com",
    "Website": "http://placehold.it/32x32",
    "BusinessType": "Sole proprietorship",
    "MainCarrer": "a",
    "RegisteredCapital": 230846.68,
    "InvestedCapital": 182686.43,
    "CharterCapital": 392048.82,
    "OwnerId": 1
  },
  {
    "TaxCode": "6280649972",
    "Name": "Tropolis",
    "ShortName": "Tr.ol",
    "Country": "Vanuatu",
    "CompanyType": "Large enterprise",
    "Address": "932 Jewel Street, Yardville, Rhode Island, 1801",
    "StartYear": 2004,
    "TelephoneNumber": "(84+) 819-5873",
    "Email": "lourdesmcleod@tropolis.com",
    "Website": "http://placehold.it/32x32",
    "BusinessType": "Partnership",
    "MainCarrer": "a",
    "RegisteredCapital": 112203.91,
    "InvestedCapital": 398844.33,
    "CharterCapital": 218882.96,
    "OwnerId": 15
  },
  {
    "TaxCode": "8505486710",
    "Name": "Ceprene",
    "ShortName": "Ce.en",
    "Country": "Mauritius",
    "CompanyType": "SMB",
    "Address": "531 Brighton Court, Jamestown, Wyoming, 151",
    "StartYear": 2005,
    "TelephoneNumber": "(84+) 967-5402",
    "Email": "lourdesmcleod@ceprene.com",
    "Website": "http://placehold.it/32x32",
    "BusinessType": "Sole proprietorship",
    "MainCarrer": "a",
    "RegisteredCapital": 135489.45,
    "InvestedCapital": 313270.33,
    "CharterCapital": 125002.54,
    "OwnerId": 5
  },
  {
    "TaxCode": "7554058843",
    "Name": "Cofine",
    "ShortName": "Co.ne",
    "Country": "Dominican Republic",
    "CompanyType": "SMB",
    "Address": "293 Crawford Avenue, Belgreen, Vermont, 4140",
    "StartYear": 2009,
    "TelephoneNumber": "(84+) 886-5883",
    "Email": "lourdesmcleod@cofine.com",
    "Website": "http://placehold.it/32x32",
    "BusinessType": "Partnership",
    "MainCarrer": "c",
    "RegisteredCapital": 138072.37,
    "InvestedCapital": 209422.71,
    "CharterCapital": 151108.39,
    "OwnerId": 2
  },
  {
    "TaxCode": "0680517127",
    "Name": "Sultrax",
    "ShortName": "Su.ra",
    "Country": "Central African Republic",
    "CompanyType": "Large enterprise",
    "Address": "166 Classon Avenue, Elbert, Guam, 6499",
    "StartYear": 2016,
    "TelephoneNumber": "(84+) 897-5303",
    "Email": "lourdesmcleod@sultrax.com",
    "Website": "http://placehold.it/32x32",
    "BusinessType": "corporation",
    "MainCarrer": "c",
    "RegisteredCapital": 188753.4,
    "InvestedCapital": 131622.55,
    "CharterCapital": 314086.38,
    "OwnerId": 4
  },
  {
    "TaxCode": "7411372287",
    "Name": "Codax",
    "ShortName": "Co.x",
    "Country": "Portugal",
    "CompanyType": "SME",
    "Address": "835 Montague Terrace, Omar, Massachusetts, 4079",
    "StartYear": 2012,
    "TelephoneNumber": "(84+) 839-5453",
    "Email": "lourdesmcleod@codax.com",
    "Website": "http://placehold.it/32x32",
    "BusinessType": "Sole proprietorship",
    "MainCarrer": "b",
    "RegisteredCapital": 136386,
    "InvestedCapital": 100227.68,
    "CharterCapital": 154362.84,
    "OwnerId": 10
  },
  {
    "TaxCode": "1966247119",
    "Name": "Vertide",
    "ShortName": "Ve.id",
    "Country": "Monaco",
    "CompanyType": "Large enterprise",
    "Address": "793 Nelson Street, Gila, Kansas, 918",
    "StartYear": 2009,
    "TelephoneNumber": "(84+) 896-5412",
    "Email": "lourdesmcleod@vertide.com",
    "Website": "http://placehold.it/32x32",
    "BusinessType": " LLC",
    "MainCarrer": "a",
    "RegisteredCapital": 367588.73,
    "InvestedCapital": 319242.17,
    "CharterCapital": 150518.06,
    "OwnerId": 19
  },
  {
    "TaxCode": "8312199891",
    "Name": "Infotrips",
    "ShortName": "In.tr",
    "Country": "Canada",
    "CompanyType": "SME",
    "Address": "797 Seigel Court, Geyserville, Indiana, 7152",
    "StartYear": 1999,
    "TelephoneNumber": "(84+) 960-5162",
    "Email": "lourdesmcleod@infotrips.com",
    "Website": "http://placehold.it/32x32",
    "BusinessType": "corporation",
    "MainCarrer": "c",
    "RegisteredCapital": 345615.57,
    "InvestedCapital": 333914.12,
    "CharterCapital": 218460.81,
    "OwnerId": 5
  },
  {
    "TaxCode": "8088201526",
    "Name": "Essensia",
    "ShortName": "Es.ns",
    "Country": "Suriname",
    "CompanyType": "Large enterprise",
    "Address": "630 Sutter Avenue, Jessie, Marshall Islands, 8197",
    "StartYear": 2020,
    "TelephoneNumber": "(84+) 850-4913",
    "Email": "lourdesmcleod@essensia.com",
    "Website": "http://placehold.it/32x32",
    "BusinessType": "corporation",
    "MainCarrer": "a",
    "RegisteredCapital": 153397.16,
    "InvestedCapital": 240157.73,
    "CharterCapital": 103278.92,
    "OwnerId": 17
  },
  {
    "TaxCode": "7715377325",
    "Name": "Visualix",
    "ShortName": "Vi.al",
    "Country": "Lithuania",
    "CompanyType": "SMB",
    "Address": "185 Schenck Place, Beason, Alaska, 2832",
    "StartYear": 2002,
    "TelephoneNumber": "(84+) 959-4743",
    "Email": "lourdesmcleod@visualix.com",
    "Website": "http://placehold.it/32x32",
    "BusinessType": "Sole proprietorship",
    "MainCarrer": "a",
    "RegisteredCapital": 353922.22,
    "InvestedCapital": 316612.25,
    "CharterCapital": 243824.81,
    "OwnerId": 17
  },
  {
    "TaxCode": "5364132956",
    "Name": "Zolar",
    "ShortName": "Zo.r",
    "Country": "S. Georgia and S. Sandwich Isls.",
    "CompanyType": "SME",
    "Address": "757 Whitwell Place, Kapowsin, Nebraska, 515",
    "StartYear": 1999,
    "TelephoneNumber": "(84+) 909-5022",
    "Email": "lourdesmcleod@zolar.com",
    "Website": "http://placehold.it/32x32",
    "BusinessType": " LLC",
    "MainCarrer": "c",
    "RegisteredCapital": 178936.49,
    "InvestedCapital": 390296.79,
    "CharterCapital": 327057.95,
    "OwnerId": 19
  },
  {
    "TaxCode": "6353021353",
    "Name": "Cytrek",
    "ShortName": "Cy.ek",
    "Country": "Cook Islands",
    "CompanyType": "Large enterprise",
    "Address": "620 Varick Avenue, Williamson, American Samoa, 531",
    "StartYear": 2012,
    "TelephoneNumber": "(84+) 899-4812",
    "Email": "lourdesmcleod@cytrek.com",
    "Website": "http://placehold.it/32x32",
    "BusinessType": " LLC",
    "MainCarrer": "a",
    "RegisteredCapital": 192735.72,
    "InvestedCapital": 365205.62,
    "CharterCapital": 392658.95,
    "OwnerId": 20
  },
  {
    "TaxCode": "3178746006",
    "Name": "Zilencio",
    "ShortName": "Zi.nc",
    "Country": "Andorra",
    "CompanyType": "SME",
    "Address": "403 Ford Street, Boomer, West Virginia, 6349",
    "StartYear": 2018,
    "TelephoneNumber": "(84+) 842-4572",
    "Email": "lourdesmcleod@zilencio.com",
    "Website": "http://placehold.it/32x32",
    "BusinessType": "corporation",
    "MainCarrer": "c",
    "RegisteredCapital": 313059.16,
    "InvestedCapital": 350662.83,
    "CharterCapital": 140358.6,
    "OwnerId": 15
  },
  {
    "TaxCode": "6925622520",
    "Name": "Niquent",
    "ShortName": "Ni.en",
    "Country": "Christmas Island",
    "CompanyType": "SME",
    "Address": "808 Waldane Court, Madaket, Virgin Islands, 3262",
    "StartYear": 2006,
    "TelephoneNumber": "(84+) 987-4393",
    "Email": "lourdesmcleod@niquent.com",
    "Website": "http://placehold.it/32x32",
    "BusinessType": "Partnership",
    "MainCarrer": "b",
    "RegisteredCapital": 189466.21,
    "InvestedCapital": 395639.24,
    "CharterCapital": 295773.33,
    "OwnerId": 12
  },
  {
    "TaxCode": "2852379641",
    "Name": "Comveyer",
    "ShortName": "Co.ey",
    "Country": "Burundi",
    "CompanyType": "SME",
    "Address": "766 Rockaway Avenue, Crayne, California, 4464",
    "StartYear": 2016,
    "TelephoneNumber": "(84+) 991-5443",
    "Email": "lourdesmcleod@comveyer.com",
    "Website": "http://placehold.it/32x32",
    "BusinessType": "corporation",
    "MainCarrer": "a",
    "RegisteredCapital": 385490.91,
    "InvestedCapital": 211332.05,
    "CharterCapital": 323869.58,
    "OwnerId": 11
  },
  {
    "TaxCode": "1332343126",
    "Name": "Rodeomad",
    "ShortName": "Ro.om",
    "Country": "Guadeloupe",
    "CompanyType": "SMB",
    "Address": "938 Bergen Place, Delwood, Virginia, 1704",
    "StartYear": 2001,
    "TelephoneNumber": "(84+) 985-5952",
    "Email": "lourdesmcleod@rodeomad.com",
    "Website": "http://placehold.it/32x32",
    "BusinessType": " LLC",
    "MainCarrer": "a",
    "RegisteredCapital": 318674.22,
    "InvestedCapital": 206012.12,
    "CharterCapital": 294753.49,
    "OwnerId": 3
  },
  {
    "TaxCode": "2424050163",
    "Name": "Retrotex",
    "ShortName": "Re.ot",
    "Country": "Mayotte",
    "CompanyType": "SMB",
    "Address": "996 Bevy Court, Fairhaven, Nevada, 9545",
    "StartYear": 2014,
    "TelephoneNumber": "(84+) 903-4833",
    "Email": "lourdesmcleod@retrotex.com",
    "Website": "http://placehold.it/32x32",
    "BusinessType": "Partnership",
    "MainCarrer": "b",
    "RegisteredCapital": 319041.08,
    "InvestedCapital": 275640.76,
    "CharterCapital": 216243.09,
    "OwnerId": 6
  },
  {
    "TaxCode": "2072706789",
    "Name": "Rubadub",
    "ShortName": "Ru.du",
    "Country": "Oman",
    "CompanyType": "SMB",
    "Address": "485 Debevoise Avenue, Sandston, New Jersey, 428",
    "StartYear": 2020,
    "TelephoneNumber": "(84+) 913-5863",
    "Email": "lourdesmcleod@rubadub.com",
    "Website": "http://placehold.it/32x32",
    "BusinessType": " LLC",
    "MainCarrer": "c",
    "RegisteredCapital": 237079.88,
    "InvestedCapital": 243590.44,
    "CharterCapital": 200700.65,
    "OwnerId": 8
  },
  {
    "TaxCode": "3132724747",
    "Name": "Geoforma",
    "ShortName": "Ge.or",
    "Country": "Somalia",
    "CompanyType": "Large enterprise",
    "Address": "894 Vandervoort Avenue, Cornucopia, Maine, 8259",
    "StartYear": 2003,
    "TelephoneNumber": "(84+) 948-4963",
    "Email": "lourdesmcleod@geoforma.com",
    "Website": "http://placehold.it/32x32",
    "BusinessType": "Sole proprietorship",
    "MainCarrer": "c",
    "RegisteredCapital": 373889.45,
    "InvestedCapital": 163903.56,
    "CharterCapital": 128845.97,
    "OwnerId": 14
  },
  {
    "TaxCode": "8975601108",
    "Name": "Uncorp",
    "ShortName": "Un.rp",
    "Country": "Chad",
    "CompanyType": "SMB",
    "Address": "926 Plymouth Street, Iberia, Mississippi, 8969",
    "StartYear": 2001,
    "TelephoneNumber": "(84+) 935-4602",
    "Email": "lourdesmcleod@uncorp.com",
    "Website": "http://placehold.it/32x32",
    "BusinessType": "Partnership",
    "MainCarrer": "a",
    "RegisteredCapital": 110667.48,
    "InvestedCapital": 340854.86,
    "CharterCapital": 284886.08,
    "OwnerId": 12
  },
  {
    "TaxCode": "0737030336",
    "Name": "Trasola",
    "ShortName": "Tr.ol",
    "Country": "Guatemala",
    "CompanyType": "SMB",
    "Address": "366 Crown Street, Macdona, Hawaii, 675",
    "StartYear": 2007,
    "TelephoneNumber": "(84+) 861-4142",
    "Email": "lourdesmcleod@trasola.com",
    "Website": "http://placehold.it/32x32",
    "BusinessType": " LLC",
    "MainCarrer": "a",
    "RegisteredCapital": 389628.38,
    "InvestedCapital": 228105.27,
    "CharterCapital": 135662.32,
    "OwnerId": 8
  },
  {
    "TaxCode": "4770704044",
    "Name": "Zidox",
    "ShortName": "Zi.x",
    "Country": "Luxembourg",
    "CompanyType": "SME",
    "Address": "987 Debevoise Street, Chelsea, Montana, 4441",
    "StartYear": 2008,
    "TelephoneNumber": "(84+) 891-5642",
    "Email": "lourdesmcleod@zidox.com",
    "Website": "http://placehold.it/32x32",
    "BusinessType": "Sole proprietorship",
    "MainCarrer": "c",
    "RegisteredCapital": 337154.67,
    "InvestedCapital": 198725.01,
    "CharterCapital": 180739.88,
    "OwnerId": 2
  },
  {
    "TaxCode": "7447324814",
    "Name": "Hairport",
    "ShortName": "Ha.po",
    "Country": "Afghanistan",
    "CompanyType": "SME",
    "Address": "473 Strong Place, Coral, New Mexico, 3726",
    "StartYear": 2017,
    "TelephoneNumber": "(84+) 987-4633",
    "Email": "lourdesmcleod@hairport.com",
    "Website": "http://placehold.it/32x32",
    "BusinessType": " LLC",
    "MainCarrer": "c",
    "RegisteredCapital": 215555.33,
    "InvestedCapital": 103577.12,
    "CharterCapital": 253936.26,
    "OwnerId": 17
  },
  {
    "TaxCode": "1531958044",
    "Name": "Lovepad",
    "ShortName": "Lo.pa",
    "Country": "Nepal",
    "CompanyType": "SMB",
    "Address": "728 Mill Lane, Lowgap, Michigan, 272",
    "StartYear": 2009,
    "TelephoneNumber": "(84+) 831-5773",
    "Email": "lourdesmcleod@lovepad.com",
    "Website": "http://placehold.it/32x32",
    "BusinessType": "Sole proprietorship",
    "MainCarrer": "c",
    "RegisteredCapital": 149018.93,
    "InvestedCapital": 208368.88,
    "CharterCapital": 313534.62,
    "OwnerId": 16
  },
  {
    "TaxCode": "8926106975",
    "Name": "Lotron",
    "ShortName": "Lo.on",
    "Country": "Russian Federation",
    "CompanyType": "SMB",
    "Address": "814 Etna Street, Abrams, District Of Columbia, 6772",
    "StartYear": 1999,
    "TelephoneNumber": "(84+) 860-5922",
    "Email": "lourdesmcleod@lotron.com",
    "Website": "http://placehold.it/32x32",
    "BusinessType": "Sole proprietorship",
    "MainCarrer": "c",
    "RegisteredCapital": 105571.23,
    "InvestedCapital": 275750.08,
    "CharterCapital": 346199.16,
    "OwnerId": 15
  },
  {
    "TaxCode": "6158444428",
    "Name": "Geekular",
    "ShortName": "Ge.ul",
    "Country": "Sri Lanka",
    "CompanyType": "Large enterprise",
    "Address": "718 John Street, Juntura, Missouri, 9552",
    "StartYear": 2001,
    "TelephoneNumber": "(84+) 967-5282",
    "Email": "lourdesmcleod@geekular.com",
    "Website": "http://placehold.it/32x32",
    "BusinessType": " LLC",
    "MainCarrer": "a",
    "RegisteredCapital": 313390.79,
    "InvestedCapital": 237828.94,
    "CharterCapital": 391700.79,
    "OwnerId": 7
  },
  {
    "TaxCode": "9102162989",
    "Name": "Freakin",
    "ShortName": "Fr.ki",
    "Country": "Macedonia",
    "CompanyType": "SMB",
    "Address": "954 Beverly Road, Swartzville, Alabama, 9625",
    "StartYear": 2013,
    "TelephoneNumber": "(84+) 946-5032",
    "Email": "lourdesmcleod@freakin.com",
    "Website": "http://placehold.it/32x32",
    "BusinessType": " LLC",
    "MainCarrer": "a",
    "RegisteredCapital": 289523.12,
    "InvestedCapital": 164901.61,
    "CharterCapital": 160778.41,
    "OwnerId": 16
  },
  {
    "TaxCode": "4621635745",
    "Name": "Injoy",
    "ShortName": "In.y",
    "Country": "Reunion",
    "CompanyType": "Large enterprise",
    "Address": "405 Vandalia Avenue, Biehle, Illinois, 8464",
    "StartYear": 2009,
    "TelephoneNumber": "(84+) 879-5533",
    "Email": "lourdesmcleod@injoy.com",
    "Website": "http://placehold.it/32x32",
    "BusinessType": " LLC",
    "MainCarrer": "b",
    "RegisteredCapital": 259300.86,
    "InvestedCapital": 208124.68,
    "CharterCapital": 317882.18,
    "OwnerId": 3
  },
  {
    "TaxCode": "4700787037",
    "Name": "Enomen",
    "ShortName": "En.en",
    "Country": "Bangladesh",
    "CompanyType": "SMB",
    "Address": "492 Garden Place, Axis, Ohio, 4127",
    "StartYear": 2021,
    "TelephoneNumber": "(84+) 986-5332",
    "Email": "lourdesmcleod@enomen.com",
    "Website": "http://placehold.it/32x32",
    "BusinessType": " LLC",
    "MainCarrer": "a",
    "RegisteredCapital": 161674.1,
    "InvestedCapital": 324068.69,
    "CharterCapital": 121140.12,
    "OwnerId": 16
  },
  {
    "TaxCode": "3848805105",
    "Name": "Mobildata",
    "ShortName": "Mo.ld",
    "Country": "French Polynesia",
    "CompanyType": "Large enterprise",
    "Address": "753 Adelphi Street, Wawona, Oklahoma, 382",
    "StartYear": 2016,
    "TelephoneNumber": "(84+) 840-5303",
    "Email": "lourdesmcleod@mobildata.com",
    "Website": "http://placehold.it/32x32",
    "BusinessType": "Partnership",
    "MainCarrer": "a",
    "RegisteredCapital": 296293.21,
    "InvestedCapital": 262713.92,
    "CharterCapital": 209603.3,
    "OwnerId": 5
  },
  {
    "TaxCode": "2895814387",
    "Name": "Endipine",
    "ShortName": "En.pi",
    "Country": "Mexico",
    "CompanyType": "SME",
    "Address": "781 Ovington Court, National, Connecticut, 4529",
    "StartYear": 2017,
    "TelephoneNumber": "(84+) 947-5653",
    "Email": "lourdesmcleod@endipine.com",
    "Website": "http://placehold.it/32x32",
    "BusinessType": " LLC",
    "MainCarrer": "a",
    "RegisteredCapital": 288234.5,
    "InvestedCapital": 226104.68,
    "CharterCapital": 242065.41,
    "OwnerId": 18
  },
  {
    "TaxCode": "3223486936",
    "Name": "Quizmo",
    "ShortName": "Qu.mo",
    "Country": "Zaire",
    "CompanyType": "Large enterprise",
    "Address": "258 Bayview Place, Trinway, Washington, 6671",
    "StartYear": 2020,
    "TelephoneNumber": "(84+) 821-5073",
    "Email": "lourdesmcleod@quizmo.com",
    "Website": "http://placehold.it/32x32",
    "BusinessType": "corporation",
    "MainCarrer": "c",
    "RegisteredCapital": 316578.61,
    "InvestedCapital": 221731.88,
    "CharterCapital": 249080.7,
    "OwnerId": 11
  },
  {
    "TaxCode": "1111924454",
    "Name": "Eventex",
    "ShortName": "Ev.te",
    "Country": "Kenya",
    "CompanyType": "SME",
    "Address": "287 Opal Court, Bagtown, Wisconsin, 3406",
    "StartYear": 2003,
    "TelephoneNumber": "(84+) 946-5733",
    "Email": "lourdesmcleod@eventex.com",
    "Website": "http://placehold.it/32x32",
    "BusinessType": "corporation",
    "MainCarrer": "c",
    "RegisteredCapital": 226653.12,
    "InvestedCapital": 203268.3,
    "CharterCapital": 151631.38,
    "OwnerId": 19
  },
  {
    "TaxCode": "4780750862",
    "Name": "Gology",
    "ShortName": "Go.gy",
    "Country": "Puerto Rico",
    "CompanyType": "SME",
    "Address": "694 Meadow Street, Stewart, Palau, 6910",
    "StartYear": 2002,
    "TelephoneNumber": "(84+) 926-4372",
    "Email": "lourdesmcleod@gology.com",
    "Website": "http://placehold.it/32x32",
    "BusinessType": "Sole proprietorship",
    "MainCarrer": "a",
    "RegisteredCapital": 167167.56,
    "InvestedCapital": 367293.47,
    "CharterCapital": 324905.24,
    "OwnerId": 2
  },
  {
    "TaxCode": "8496083525",
    "Name": "Tripsch",
    "ShortName": "Tr.sc",
    "Country": "Guyana",
    "CompanyType": "Large enterprise",
    "Address": "972 Herkimer Place, Kenwood, Kentucky, 2601",
    "StartYear": 2010,
    "TelephoneNumber": "(84+) 953-4213",
    "Email": "lourdesmcleod@tripsch.com",
    "Website": "http://placehold.it/32x32",
    "BusinessType": "corporation",
    "MainCarrer": "c",
    "RegisteredCapital": 298052.48,
    "InvestedCapital": 386826.56,
    "CharterCapital": 115227.3,
    "OwnerId": 6
  },
  {
    "TaxCode": "2223886903",
    "Name": "Endicil",
    "ShortName": "En.ci",
    "Country": "Benin",
    "CompanyType": "Large enterprise",
    "Address": "265 Cortelyou Road, Dupuyer, New York, 9839",
    "StartYear": 2000,
    "TelephoneNumber": "(84+) 903-4252",
    "Email": "lourdesmcleod@endicil.com",
    "Website": "http://placehold.it/32x32",
    "BusinessType": "Sole proprietorship",
    "MainCarrer": "c",
    "RegisteredCapital": 396395.02,
    "InvestedCapital": 318221.02,
    "CharterCapital": 339814.15,
    "OwnerId": 10
  },
  {
    "TaxCode": "5584746505",
    "Name": "Digigen",
    "ShortName": "Di.ge",
    "Country": "Pakistan",
    "CompanyType": "Large enterprise",
    "Address": "751 Lincoln Avenue, Yonah, Oregon, 4015",
    "StartYear": 2005,
    "TelephoneNumber": "(84+) 927-5143",
    "Email": "lourdesmcleod@digigen.com",
    "Website": "http://placehold.it/32x32",
    "BusinessType": "Partnership",
    "MainCarrer": "a",
    "RegisteredCapital": 358340.53,
    "InvestedCapital": 179925.35,
    "CharterCapital": 216502.82,
    "OwnerId": 9
  },
  {
    "TaxCode": "6294051053",
    "Name": "Multron",
    "ShortName": "Mu.ro",
    "Country": "Guinea-Bissau",
    "CompanyType": "SME",
    "Address": "457 Prescott Place, Whipholt, Delaware, 9261",
    "StartYear": 2004,
    "TelephoneNumber": "(84+) 833-5543",
    "Email": "lourdesmcleod@multron.com",
    "Website": "http://placehold.it/32x32",
    "BusinessType": "corporation",
    "MainCarrer": "b",
    "RegisteredCapital": 177536.64,
    "InvestedCapital": 209831.25,
    "CharterCapital": 291177.12,
    "OwnerId": 1
  }
]